Boosting/Probit.py
Boosting/__init__.py
Boosting_Probit-0.0.1.dist-info/LICENSE.txt
Boosting_Probit-0.0.1.dist-info/METADATA
Boosting_Probit-0.0.1.dist-info/WHEEL
Boosting_Probit-0.0.1.dist-info/top_level.txt
Boosting_Probit-0.0.1.dist-info/RECORD
